<?xml version="1.0"?>
<page xmlns:xsi="http://www.w3.org/2001/XMLSchema-instance"
      layout="1column" xsi:noNamespaceSchemaLocation="urn:magento:framework:View/Layout/etc/page_configuration.xsd">
    <body>
        <referenceBlock name="catalog.product.related" remove="true"/>
        <referenceBlock name="product.info.upsell" remove="true"/>
        <referenceBlock name="header.container" remove="true"/>
        <referenceBlock name="footer-container" remove="true"/>
        <referenceBlock name="page.top" remove="true" />
        <referenceBlock name="copyright" remove="true" />
        <referenceBlock name="authentication-popup" remove="true" />
        <referenceBlock name="product.info.review" remove="true" />
        <referenceBlock name="product.info.mailto" remove="true" />
        <referenceBlock name="product.info.addto" remove="true" />
        <referenceBlock name="product.info.details" remove="true" />
        <referenceBlock name="content.aside" remove="true" />
        <block class="Magento\Checkout\Block\Onepage\Success" name="checkout.success" template="Magento_Checkout::success.phtml" cacheable="false">
            <container name="order.success.additional.info" label="Order Success Additional Info"/>
        </block>
        <block class="Magento\Checkout\Block\Registration" name="checkout.registration" template="Magento_Checkout::registration.phtml" cacheable="false"/>
    </body>
</page>
